email2pdf2/__init__.py
email2pdf2/__main__.py
email2pdf2/_version.py
email2pdf2/cmd.py
email2pdf2/email2pdf2.py
email2pdf2-0.0.3.dist-info/LICENSE.txt
email2pdf2-0.0.3.dist-info/METADATA
email2pdf2-0.0.3.dist-info/WHEEL
email2pdf2-0.0.3.dist-info/entry_points.txt
email2pdf2-0.0.3.dist-info/top_level.txt
email2pdf2-0.0.3.dist-info/RECORD
